{
  "admin": {
    "anima": -1,
    "eidolon": -1,
    "hada": -1,
    "fantasma": -1,
    "minerva": -1
  },
  "Test": { "anima": 3, "eidolon": 3, "hada": 3, "fantasma": 3, "minerva": 0 },
  "S33D": { "anima": 3, "eidolon": 3, "hada": 3, "fantasma": 3, "minerva": 0 },
  "RAM-1": { "anima": 3, "eidolon": 3, "hada": 3, "fantasma": 3, "minerva": 0 },
  "SV3ZD4": { "anima": 3, "eidolon": 3, "hada": 3, "fantasma": 3, "minerva": 0 },
  "L30N4": { "anima": 3, "eidolon": 3, "hada": 3, "fantasma": 3, "minerva": 0 },
  "CH3SHIR3": { "anima": 3, "eidolon": 3, "hada": 3, "fantasma": 3, "minerva": 0 },
  "M7RDD1N": { "anima": 3, "eidolon": 3, "hada": 3, "fantasma": 3, "minerva": 0 },
  "SK14": { "anima": 3, "eidolon": 3, "hada": 3, "fantasma": 3, "minerva": 0 },
  "M0R14RT7": { "anima": 3, "eidolon": 3, "hada": 3, "fantasma": 3, "minerva": 0 },
  "MM": { "anima": 3, "eidolon": 3, "hada": 3, "fantasma": 3, "minerva": 0 },
  "3RR4NT3": { "anima": 3, "eidolon": 3, "hada": 3, "fantasma": 3, "minerva": 0 },
  "3P1ST3M3": { "anima": 3, "eidolon": 3, "hada": 3, "fantasma": 3, "minerva": 0 },
  "L4ZH0R": { "anima": 3, "eidolon": 3, "hada": 3, "fantasma": 3, "minerva": 0 },
  "D14BL0": { "anima": 3, "eidolon": 3, "hada": 3, "fantasma": 3, "minerva": 0 },
  "LUC3R0": { "anima": 3, "eidolon": 3, "hada": 3, "fantasma": 3, "minerva": 0 },
  "4N4T0L4": { "anima": 3, "eidolon": 3, "hada": 3, "fantasma": 3, "minerva": 0 },
  "R3QU13M": { "anima": 3, "eidolon": 3, "hada": 3, "fantasma": 3, "minerva": 0 },
  "54R13L": { "anima": 3, "eidolon": 3, "hada": 3, "fantasma": 3, "minerva": 0 },
  "V3X4": { "anima": 3, "eidolon": 3, "hada": 3, "fantasma": 3, "minerva": 0 },
  "4L3X": { "anima": 3, "eidolon": 3, "hada": 3, "fantasma": 3, "minerva": 0 },
  "S1B1L4": { "anima": 3, "eidolon": 3, "hada": 3, "fantasma": 3, "minerva": 0 },
  "3L1A5": { "anima": 3, "eidolon": 3, "hada": 3, "fantasma": 3, "minerva": 0 },
  "L0C0": { "anima": 3, "eidolon": 3, "hada": 3, "fantasma": 3, "minerva": 0 },
  "D4N43": { "anima": 3, "eidolon": 3, "hada": 3, "fantasma": 3, "minerva": 0 },
  "B4N74": { "anima": 3, "eidolon": 3, "hada": 3, "fantasma": 3, "minerva": 0 }
}
